odoo/addons/l10n_br_fiscal_certificate/README.rst
odoo/addons/l10n_br_fiscal_certificate/__init__.py
odoo/addons/l10n_br_fiscal_certificate/__manifest__.py
odoo/addons/l10n_br_fiscal_certificate/constants.py
odoo/addons/l10n_br_fiscal_certificate/hooks.py
odoo/addons/l10n_br_fiscal_certificate/i18n/l10n_br_fiscal_certificate.pot
odoo/addons/l10n_br_fiscal_certificate/i18n/pt_BR.po
odoo/addons/l10n_br_fiscal_certificate/models/__init__.py
odoo/addons/l10n_br_fiscal_certificate/models/certificate.py
odoo/addons/l10n_br_fiscal_certificate/models/res_company.py
odoo/addons/l10n_br_fiscal_certificate/models/res_config_settings.py
odoo/addons/l10n_br_fiscal_certificate/readme/CONTRIBUTORS.md
odoo/addons/l10n_br_fiscal_certificate/readme/DESCRIPTION.md
odoo/addons/l10n_br_fiscal_certificate/readme/HISTORY.md
odoo/addons/l10n_br_fiscal_certificate/readme/USAGE.md
odoo/addons/l10n_br_fiscal_certificate/security/ir.model.access.csv
odoo/addons/l10n_br_fiscal_certificate/static/description/icon.png
odoo/addons/l10n_br_fiscal_certificate/static/description/index.html
odoo/addons/l10n_br_fiscal_certificate/tests/__init__.py
odoo/addons/l10n_br_fiscal_certificate/tests/test_certificate.py
odoo/addons/l10n_br_fiscal_certificate/views/certificate_view.xml
odoo/addons/l10n_br_fiscal_certificate/views/res_company_view.xml
odoo/addons/l10n_br_fiscal_certificate/views/res_config_settings_view.xml
odoo_addon_l10n_br_fiscal_certificate-18.0.1.2.0.dist-info/METADATA
odoo_addon_l10n_br_fiscal_certificate-18.0.1.2.0.dist-info/WHEEL
odoo_addon_l10n_br_fiscal_certificate-18.0.1.2.0.dist-info/top_level.txt
odoo_addon_l10n_br_fiscal_certificate-18.0.1.2.0.dist-info/RECORD
