Metadata-Version: 2.1
Name: odoo-addon-l10n_br_fiscal_certificate
Version: 18.0.1.2.0
Requires-Python: >=3.10
Requires-Dist: erpbrasil.assinatura
Requires-Dist: odoo-addon-l10n_br_fiscal==18.0.*
Requires-Dist: odoo==18.0.*
Summary: A1 fiscal certificate management for Brazil
Home-page: https://github.com/OCA/l10n-brazil
License: AGPL-3
Author: Akretion, Odoo Community Association (OCA)
Author-email: support@odoo-community.org
Classifier: Programming Language :: Python
Classifier: Framework :: Odoo
Classifier: Framework :: Odoo :: 18.0
Classifier: License :: OSI Approved :: GNU Affero General Public License v3
Classifier: Development Status :: 5 - Production/Stable
